ogr2vrt_simple/__init__.py
ogr2vrt_simple/cli.py
ogr2vrt_simple/templates/__init__.py
ogr2vrt_simple/templates/vrt.j2
ogr2vrt_simple/utils/__init__.py
ogr2vrt_simple/utils/data_structures.py
ogr2vrt_simple/utils/io_utils.py
ogr2vrt_simple/utils/ogr_utils.py
ogr2vrt_simple/utils/string_utils.py
ogr2vrt_simple/vrt_data_sources/__init__.py
ogr2vrt_simple/vrt_data_sources/abstract_source.py
ogr2vrt_simple/vrt_data_sources/file_source.py
ogr2vrt_simple/vrt_data_sources/http_source.py
ogr2vrt_simple-0.2.4.dist-info/LICENSE
ogr2vrt_simple-0.2.4.dist-info/METADATA
ogr2vrt_simple-0.2.4.dist-info/WHEEL
ogr2vrt_simple-0.2.4.dist-info/entry_points.txt
ogr2vrt_simple-0.2.4.dist-info/RECORD
