Metadata-Version: 2.1
Name: ogr2vrt-simple
Version: 0.2.4
Summary: Generate a simple VRT file for data transformations
Home-page: https://github.com/jeanpommier/ogr2vrt_simple/
Keywords: gdal,ogr,VRT,geospatial
Author: Jean Pommier
Author-email: jean.pommier@pi-geosolutions.fr
Requires-Python: >=3.8,<4.0
Classifier: Programming Language :: Python :: 3
Classifier: Programming Language :: Python :: 3.8
Classifier: Programming Language :: Python :: 3.9
Classifier: Programming Language :: Python :: 3.10
Classifier: Programming Language :: Python :: 3.11
Requires-Dist: charset-normalizer (>=3.3.2,<4.0.0)
Requires-Dist: click (>=8.1.7,<9.0.0)
Requires-Dist: humanize (>=4.8.0,<5.0.0)
Requires-Dist: importlib-resources (>=6.1.1,<7.0.0) ; python_version < "3.9"
Requires-Dist: jinja2 (>=3.1.2,<4.0.0)
Requires-Dist: markupsafe (>=2.1.3,<3.0.0)
Requires-Dist: py7zr (>=0.20.7,<0.21.0)
Requires-Dist: rarfile (>=4.1,<5.0)
Requires-Dist: unidecode (>=1.3.7,<2.0.0)
Requires-Dist: wheel (>=0.41.3,<0.42.0)
Project-URL: Repository, https://github.com/jeanpommier/ogr2vrt_simple/
